sensordroid/__init__.py
sensordroid-2.1.3.4.dist-info/METADATA
sensordroid-2.1.3.4.dist-info/WHEEL
sensordroid-2.1.3.4.dist-info/top_level.txt
sensordroid-2.1.3.4.dist-info/RECORD
