Metadata-Version: 2.1
Name: sensordroid
Version: 2.1.3.4
Summary: Sensor Droid - Streams, in real-time, sensors and camera data directly to a client device over wireless network.
Home-page: https://sites.google.com/view/sensordroid/
Author: Tarek Moghrabi
Author-email: moghrabi.tarek@outlook.com
License: Proprietary
Platform: UNKNOWN
Classifier: Programming Language :: Python :: 3
Classifier: License :: Other/Proprietary License
Classifier: Operating System :: OS Independent
